lakeflow_jobs_meta/__init__.py
lakeflow_jobs_meta/constants.py
lakeflow_jobs_meta/main.py
lakeflow_jobs_meta/metadata_manager.py
lakeflow_jobs_meta/monitor.py
lakeflow_jobs_meta/orchestrator.py
lakeflow_jobs_meta/task_builders.py
lakeflow_jobs_meta/utils.py
lakeflow_jobs_meta-0.1.1.dist-info/licenses/LICENSE
lakeflow_jobs_meta-0.1.1.dist-info/METADATA
lakeflow_jobs_meta-0.1.1.dist-info/WHEEL
lakeflow_jobs_meta-0.1.1.dist-info/entry_points.txt
lakeflow_jobs_meta-0.1.1.dist-info/top_level.txt
lakeflow_jobs_meta-0.1.1.dist-info/RECORD
