Metadata-Version: 2.4
Name: lakeflow-jobs-meta
Version: 0.1.1
Summary: Metadata-driven framework for orchestrating Databricks Lakeflow Jobs
Home-page: https://github.com/park-peter/lakeflow-jobs-meta
Author: Peter Park
Author-email: Peter Park <peter.park@databricks.com>
License: Apache-2.0
Project-URL: Homepage, https://github.com/park-peter/lakeflow-jobs-meta
Project-URL: Documentation, https://github.com/park-peter/lakeflow-jobs-meta/blob/main/README.md
Project-URL: Repository, https://github.com/park-peter/lakeflow-jobs-meta
Project-URL: Issues, https://github.com/park-peter/lakeflow-jobs-meta/issues
Keywords: databricks,jobs,orchestration,metadata,workflow,etl,data-engineering
Classifier: Development Status :: 4 - Beta
Classifier: Intended Audience :: Developers
Classifier: Intended Audience :: Information Technology
Classifier: License :: OSI Approved :: Apache Software License
Classifier: Operating System :: OS Independent
Classifier: Programming Language :: Python :: 3
Classifier: Programming Language :: Python :: 3.10
Classifier: Programming Language :: Python :: 3.11
Classifier: Programming Language :: Python :: 3.12
Classifier: Programming Language :: Python :: 3.13
Classifier: Programming Language :: Python :: 3.14
Classifier: Topic :: Software Development :: Libraries :: Python Modules
Classifier: Topic :: Database
Requires-Python: >=3.10
License-File: LICENSE
Requires-Dist: databricks-sdk>=0.65.0
Provides-Extra: dev
Requires-Dist: pytest>=7.0.0; extra == "dev"
Requires-Dist: pytest-cov>=4.0.0; extra == "dev"
Requires-Dist: pytest-mock>=3.12.0; extra == "dev"
Requires-Dist: delta-spark>=3.2.0; extra == "dev"
Requires-Dist: pyspark>=3.5.0; extra == "dev"
Requires-Dist: pyyaml>=6.0; extra == "dev"
Dynamic: author
Dynamic: home-page
Dynamic: license-file
Dynamic: requires-python
